turkish_string/__init__.py
turkish_string/base.py
turkish_string-1.0.0.dist-info/METADATA
turkish_string-1.0.0.dist-info/WHEEL
turkish_string-1.0.0.dist-info/licenses/LICENSE
turkish_string-1.0.0.dist-info/RECORD
