Metadata-Version: 2.1
Name: turkish-string
Version: 1.0.0
Summary: Provides alternative string methods to Python's built-in upper(), lower(), capitalize() and title() that work for turkish characters.
Project-URL: Homepage, https://github.com/o-sari/turkish-string
Project-URL: Repository, https://github.com/o-sari/turkish-string
Project-URL: Issues, https://github.com/o-sari/turkish-string/issues
Author-email: Omer Faruk Sari <info@aqilan.com>
Maintainer-email: Omer Faruk Sari <info@aqilan.com>
License: BSD 3-Clause License
License-File: LICENSE
Keywords: capitalize,capitalize(),encoding,lower,lower(),title,title(),turkish,upper,upper()
Classifier: Development Status :: 5 - Production/Stable
Classifier: Intended Audience :: Developers
Classifier: License :: OSI Approved :: BSD License
Classifier: Operating System :: OS Independent
Classifier: Programming Language :: Python
Classifier: Programming Language :: Python :: 3
Classifier: Programming Language :: Python :: 3 :: Only
Classifier: Programming Language :: Python :: 3.8
Classifier: Programming Language :: Python :: 3.9
Classifier: Programming Language :: Python :: 3.10
Classifier: Programming Language :: Python :: 3.11
Classifier: Programming Language :: Python :: 3.12
Requires-Python: >=3.8
